mkdocs_deploy/__init__.py
mkdocs_deploy/__main__.py
mkdocs_deploy/abstract.py
mkdocs_deploy/actions.py
mkdocs_deploy/configuration.py
mkdocs_deploy/main.py
mkdocs_deploy/mkdocs_plugin.py
mkdocs_deploy/plugins/__init__.py
mkdocs_deploy/plugins/aws_s3.py
mkdocs_deploy/plugins/local_filesystem.py
mkdocs_deploy/shared_implementations.py
mkdocs_deploy/versions.py
mkdocs_deploy-0.1.3.dist-info/LICENSE
mkdocs_deploy-0.1.3.dist-info/METADATA
mkdocs_deploy-0.1.3.dist-info/WHEEL
mkdocs_deploy-0.1.3.dist-info/entry_points.txt
mkdocs_deploy-0.1.3.dist-info/RECORD
