Metadata-Version: 2.1
Name: mkdocs-deploy
Version: 0.1.3
Summary: Mkdocs versioning and deployment tool
License: Apache-2.0
Author: Philip Couling
Author-email: couling@gmail.com
Requires-Python: >=3.8,<4.0
Classifier: License :: OSI Approved :: Apache Software License
Classifier: Programming Language :: Python :: 3
Classifier: Programming Language :: Python :: 3.8
Classifier: Programming Language :: Python :: 3.9
Classifier: Programming Language :: Python :: 3.10
Classifier: Programming Language :: Python :: 3.11
Classifier: Programming Language :: Python :: 3.12
Requires-Dist: boto3 (>=1.26.45)
Requires-Dist: click (>=8.0,<9.0)
Requires-Dist: pydantic (>=1.10.4,<2.0.0)
Requires-Dist: pyyaml (>=6.0)
Requires-Dist: toml (>=0.10.2)
